{
  "LOGGEDIN_VERSION": 2,
  "TIMEOUT_DEFAULT": 15000,
  "TIMEOUT_DETAILS": [
    {
      "url": "app.bsky.video.uploadVideo",
      "timeout": 600000
    },
    {
      "url": "com.atproto.repo.uploadBlob",
      "timeout": 150000
    },
    {
      "url": "com.atproto.sync.getBlob",
      "timeout": 150000
    }
  ],
  "INTERVAL_OF_UPDATE_JWT": 60000,
  "DEFAULT_NOTIFICATION_FETCH_INTERVAL": 15000,
  "DEFAULT_TIMELINE_FETCH_INTERVAL": 10000,
  "LABELER_UPPER_LIMIT": 20,
  "OFFICIAL_LABELER_DID": "did:plc:ar7c4by46qjdydhdevvrndac",
  "OFFICIAL_SPECIAL_LABELERS": [
    "nudity",
    "graphic-media",
    "sexual",
    "porn"
  ],
  "LIMIT_OF_FETCH_ACTORS_TYPEAHEAD": 10,
  "LIMIT_OF_FETCH_ACTORS_TYPEAHEAD_IN_CHAT_MEMBERS": 30,
  "LIMIT_OF_FETCH_AUTHOR_FEEDS": 30,
  "LIMIT_OF_FETCH_AUTHOR_REPOSTS": 20,
  "LIMIT_OF_FETCH_AUTHOR_LIKES": 20,
  "LIMIT_OF_FETCH_AUTHOR_LIST": 100,
  "LIMIT_OF_FETCH_AUTHOR_CUSTOM_FEEDS": 30,
  "LIMIT_OF_FETCH_AUTHOR_STARTER_PACKS": 30,
  "LIMIT_OF_FETCH_BLOCKING_USERS": 30,
  "LIMIT_OF_FETCH_CUSTOM_BOOKMARKS": 25,
  "LIMIT_OF_FETCH_FEEDS": 30,
  "LIMIT_OF_FETCH_FOLLOWS": 30,
  "LIMIT_OF_FETCH_LIKE_USERS": 30,
  "LIMIT_OF_FETCH_MY_LIST": 100,
  "LIMIT_OF_FETCH_MY_LIST_ITERATION": 10,
  "LIMIT_OF_FETCH_MY_LIST_USERS": 100,
  "LIMIT_OF_FETCH_MY_LIST_USERS_ITERATION": 50,
  "LIMIT_OF_FETCH_LIST_FEEDS": 30,
  "LIMIT_OF_FETCH_LIST_ITEMS": 30,
  "LIMIT_OF_FETCH_MUTING_USERS": 30,
  "LIMIT_OF_FETCH_MY_FEEDS": 30,
  "LIMIT_OF_FETCH_NOTIFICATIONS": 100,
  "LIMIT_OF_FETCH_POPULAR_FEED_GENERATORS": 30,
  "LIMIT_OF_FETCH_POST_THREAD": 8,
  "LIMIT_OF_FETCH_POSTS": 25,
  "LIMIT_OF_FETCH_QUOTE_REPOSTS": 30,
  "LIMIT_OF_FETCH_REPOST_USERS": 30,
  "LIMIT_OF_FETCH_POST_SEARCH": 30,
  "LIMIT_OF_FETCH_SUGGESTION_SEARCH": 30,
  "LIMIT_OF_FETCH_TIMELINE": 45,
  "LIMIT_OF_FETCH_USER_SEARCH": 30,
  "LIMIT_OF_KEYWORD_HISTORY": 10,
  "LIMIT_OF_THREADGATE_ITEMS": 5,
  "LIMIT_OF_LIST_MENTION_ACCOUNTS": 30,
  "THIRD_PARTY_DOMAIN_BOOKMARK": "space.aoisora.bookmark",
  "THIRD_PARTY_DOMAIN_LIGHTNING": "space.aoisora.post.lightning",
  "THIRD_PARTY_DOMAIN_VIA": "space.aoisora.post.via"
}
